AUTHORS
COPYING
MANIFEST.in
README.rst
setup.py
rayopt/__init__.py
rayopt/_transformations.c
rayopt/analysis.py
rayopt/cachend.py
rayopt/codev.py
rayopt/conjugates.py
rayopt/elements.py
rayopt/formats.py
rayopt/gaussian_trace.py
rayopt/geometric_trace.py
rayopt/library.py
rayopt/library.sqlite
rayopt/library_items.py
rayopt/material.py
rayopt/name_mixin.py
rayopt/optimize.py
rayopt/oslo.py
rayopt/paraxial_trace.py
rayopt/poly_trace.py
rayopt/pupils.py
rayopt/raytrace.py
rayopt/rii.py
rayopt/simplex.py
rayopt/simplex_accel.c
rayopt/simplex_accel.pyx
rayopt/special_sums.py
rayopt/system.py
rayopt/transformations.py
rayopt/utils.py
rayopt/zemax.py
rayopt.egg-info/PKG-INFO
rayopt.egg-info/SOURCES.txt
rayopt.egg-info/dependency_links.txt
rayopt.egg-info/requires.txt
rayopt.egg-info/top_level.txt
rayopt/test/__init__.py
rayopt/test/test_analysis.py
rayopt/test/test_cachend.py
rayopt/test/test_conjugates.py
rayopt/test/test_elements.py
rayopt/test/test_poly.py
rayopt/test/test_raytrace.py
rayopt/test/test_seidel.py
rayopt/test/test_utils.py
rayopt/test/test_yaml.py