Metadata-Version: 1.1
Name: rayopt
Version: 0.2
Summary: raytracing and lens design framework
Home-page: https://github.com/jordens/rayopt
Author: Robert Jordens
Author-email: robert@joerdens.org
License: LGPLv3+
Keywords: optics lens design raytracing optimization point spread opd aberration
Platform: UNKNOWN
Classifier: Development Status :: 5 - Production/Stable
Classifier: Intended Audience :: Science/Research
Classifier: License :: OSI Approved :: GNU Lesser General Public License v3 or later (LGPLv3+)
Classifier: Operating System :: OS Independent
Classifier: Programming Language :: Python :: 2
Classifier: Programming Language :: Python :: 3
Classifier: Topic :: Scientific/Engineering :: Physics
